jac_scale/__init__.py
jac_scale/config_loader.jac
jac_scale/context.jac
jac_scale/google_sso_provider.jac
jac_scale/memory_hierarchy.jac
jac_scale/plugin.jac
jac_scale/plugin_config.jac
jac_scale/serve.jac
jac_scale/sso_provider.jac
jac_scale/user_manager.jac
jac_scale/utils.jac
jac_scale/webhook.jac
jac_scale/abstractions/database_provider.jac
jac_scale/abstractions/deployment_target.jac
jac_scale/abstractions/image_registry.jac
jac_scale/abstractions/logger.jac
jac_scale/abstractions/config/app_config.jac
jac_scale/abstractions/config/base_config.jac
jac_scale/abstractions/models/deployment_result.jac
jac_scale/abstractions/models/resource_status.jac
jac_scale/factories/database_factory.jac
jac_scale/factories/deployment_factory.jac
jac_scale/factories/registry_factory.jac
jac_scale/factories/storage_factory.jac
jac_scale/factories/utility_factory.jac
jac_scale/impl/config_loader.impl.jac
jac_scale/impl/context.impl.jac
jac_scale/impl/memory_hierarchy.main.impl.jac
jac_scale/impl/memory_hierarchy.mongo.impl.jac
jac_scale/impl/memory_hierarchy.redis.impl.jac
jac_scale/impl/serve.impl.jac
jac_scale/impl/user_manager.impl.jac
jac_scale/impl/webhook.impl.jac
jac_scale/jserver/__init__.py
jac_scale/jserver/jfast_api.jac
jac_scale/jserver/jserver.jac
jac_scale/jserver/impl/jfast_api.impl.jac
jac_scale/jserver/impl/jserver.impl.jac
jac_scale/providers/database/kubernetes_mongo.jac
jac_scale/providers/database/kubernetes_redis.jac
jac_scale/providers/registry/dockerhub.jac
jac_scale/targets/kubernetes/kubernetes_config.jac
jac_scale/targets/kubernetes/kubernetes_target.jac
jac_scale/targets/kubernetes/utils/kubernetes_utils.impl.jac
jac_scale/targets/kubernetes/utils/kubernetes_utils.jac
jac_scale/tests/__init__.py
jac_scale/tests/conftest.py
jac_scale/tests/test_abstractions.py
jac_scale/tests/test_deploy_k8s.py
jac_scale/tests/test_examples.py
jac_scale/tests/test_factories.py
jac_scale/tests/test_file_upload.py
jac_scale/tests/test_hooks.py
jac_scale-0.1.4.dist-info/METADATA
jac_scale-0.1.4.dist-info/WHEEL
jac_scale-0.1.4.dist-info/entry_points.txt
jac_scale-0.1.4.dist-info/top_level.txt
jac_scale-0.1.4.dist-info/RECORD
