Metadata-Version: 2.4
Name: jac-scale
Version: 0.1.4
Author-email: Jason Mars <jason@mars.ninja>
Requires-Python: >=3.12
Requires-Dist: jaclang>=0.9.13
Requires-Dist: python-dotenv<2.0.0,>=1.2.1
Requires-Dist: docker<8.0.0,>=7.1.0
Requires-Dist: kubernetes<35.0.0,>=34.1.0
Requires-Dist: pymongo<5.0.0,>=4.15.4
Requires-Dist: redis<8.0.0,>=7.1.0
Requires-Dist: fastapi<0.122.0,>=0.121.3
Requires-Dist: uvicorn<0.39.0,>=0.38.0
Requires-Dist: pyjwt<2.11.0,>=2.10.1
Requires-Dist: fastapi-sso<1.0.0,>=0.18.0
Requires-Dist: python-multipart<1.0.0,>=0.0.21
